{
  "genders": [
    0
  ],
  "ages_ranges": [
    {
      "max": 65,
      "min": 13
    }
  ],
  "geo_locations": [
    {
      "pySocialWatcherReference": "0",
      "values": [
        {
          "latitude": 8.112042,
          "distance_unit": "kilometer",
          "radius": 1,
          "longitude": -72.488626
        }
      ],
      "name": "custom_locations",
      "location_types": [
        "home",
        "recent"
      ]
    },
    {
      "pySocialWatcherReference": "1",
      "values": [
        {
          "latitude": 7.935925,
          "distance_unit": "kilometer",
          "radius": 1,
          "longitude": -72.508824
        }
      ],
      "name": "custom_locations",
      "location_types": [
        "home",
        "recent"
      ]
    },
    {
      "pySocialWatcherReference": "2",
      "values": [
        {
          "latitude": 7.954265,
          "distance_unit": "kilometer",
          "radius": 1,
          "longitude": -72.503871
        }
      ],
      "name": "custom_locations",
      "location_types": [
        "home",
        "recent"
      ]
    },
    {
      "pySocialWatcherReference": "3",
      "values": [
        {
          "latitude": 7.956976,
          "distance_unit": "kilometer",
          "radius": 1,
          "longitude": -72.479813
        }
      ],
      "name": "custom_locations",
      "location_types": [
        "home",
        "recent"
      ]
    },
    {
      "pySocialWatcherReference": "4",
      "values": [
        {
          "latitude": 7.926413,
          "distance_unit": "kilometer",
          "radius": 1,
          "longitude": -72.546121
        }
      ],
      "name": "custom_locations",
      "location_types": [
        "home",
        "recent"
      ]
    },
    {
      "pySocialWatcherReference": "5",
      "values": [
        {
          "latitude": 7.949396,
          "distance_unit": "kilometer",
          "radius": 1,
          "longitude": -72.522443
        }
      ],
      "name": "custom_locations",
      "location_types": [
        "home",
        "recent"
      ]
    },
    {
      "pySocialWatcherReference": "6",
      "values": [
        {
          "latitude": 7.927185,
          "distance_unit": "kilometer",
          "radius": 1,
          "longitude": -72.476091
        }
      ],
      "name": "custom_locations",
      "location_types": [
        "home",
        "recent"
      ]
    },
    {
      "pySocialWatcherReference": "7",
      "values": [
        {
          "latitude": 7.917746,
          "distance_unit": "kilometer",
          "radius": 1,
          "longitude": -72.513932
        }
      ],
      "name": "custom_locations",
      "location_types": [
        "home",
        "recent"
      ]
    },
    {
      "pySocialWatcherReference": "8",
      "values": [
        {
          "latitude": 7.912639,
          "distance_unit": "kilometer",
          "radius": 1,
          "longitude": -72.463251
        }
      ],
      "name": "custom_locations",
      "location_types": [
        "home",
        "recent"
      ]
    },
    {
      "pySocialWatcherReference": "9",
      "values": [
        {
          "latitude": 7.898864,
          "distance_unit": "kilometer",
          "radius": 1,
          "longitude": -72.518806
        }
      ],
      "name": "custom_locations",
      "location_types": [
        "home",
        "recent"
      ]
    },
    {
      "pySocialWatcherReference": "10",
      "values": [
        {
          "latitude": 7.904203,
          "distance_unit": "kilometer",
          "radius": 1,
          "longitude": -72.500468
        }
      ],
      "name": "custom_locations",
      "location_types": [
        "home",
        "recent"
      ]
    },
    {
      "pySocialWatcherReference": "11",
      "values": [
        {
          "latitude": 7.908693,
          "distance_unit": "kilometer",
          "radius": 1,
          "longitude": -72.481586
        }
      ],
      "name": "custom_locations",
      "location_types": [
        "home",
        "recent"
      ]
    },
    {
      "pySocialWatcherReference": "12",
      "values": [
        {
          "latitude": 7.876198,
          "distance_unit": "kilometer",
          "radius": 1,
          "longitude": -72.473847
        }
      ],
      "name": "custom_locations",
      "location_types": [
        "home",
        "recent"
      ]
    },
    {
      "pySocialWatcherReference": "13",
      "values": [
        {
          "latitude": 7.880911,
          "distance_unit": "kilometer",
          "radius": 1,
          "longitude": -72.524225
        }
      ],
      "name": "custom_locations",
      "location_types": [
        "home",
        "recent"
      ]
    },
    {
      "pySocialWatcherReference": "14",
      "values": [
        {
          "latitude": 7.885633,
          "distance_unit": "kilometer",
          "radius": 1,
          "longitude": -72.505728
        }
      ],
      "name": "custom_locations",
      "location_types": [
        "home",
        "recent"
      ]
    },
    {
      "pySocialWatcherReference": "15",
      "values": [
        {
          "latitude": 7.890666,
          "distance_unit": "kilometer",
          "radius": 1,
          "longitude": -72.487004
        }
      ],
      "name": "custom_locations",
      "location_types": [
        "home",
        "recent"
      ]
    },
    {
      "pySocialWatcherReference": "16",
      "values": [
        {
          "latitude": 7.894459,
          "distance_unit": "kilometer",
          "radius": 1,
          "longitude": -72.468518
        }
      ],
      "name": "custom_locations",
      "location_types": [
        "home",
        "recent"
      ]
    },
    {
      "pySocialWatcherReference": "17",
      "values": [
        {
          "latitude": 7.889353,
          "distance_unit": "kilometer",
          "radius": 1,
          "longitude": -72.555876
        }
      ],
      "name": "custom_locations",
      "location_types": [
        "home",
        "recent"
      ]
    },
    {
      "pySocialWatcherReference": "18",
      "values": [
        {
          "latitude": 7.876274,
          "distance_unit": "kilometer",
          "radius": 1,
          "longitude": -72.542486
        }
      ],
      "name": "custom_locations",
      "location_types": [
        "home",
        "recent"
      ]
    },
    {
      "pySocialWatcherReference": "19",
      "values": [
        {
          "latitude": 7.872797,
          "distance_unit": "kilometer",
          "radius": 1,
          "longitude": -72.491953
        }
      ],
      "name": "custom_locations",
      "location_types": [
        "home",
        "recent"
      ]
    },
    {
      "pySocialWatcherReference": "20",
      "values": [
        {
          "latitude": 7.894919,
          "distance_unit": "kilometer",
          "radius": 1,
          "longitude": -72.537604
        }
      ],
      "name": "custom_locations",
      "location_types": [
        "home",
        "recent"
      ]
    },
    {
      "pySocialWatcherReference": "21",
      "values": [
        {
          "latitude": 7.913025,
          "distance_unit": "kilometer",
          "radius": 1,
          "longitude": -72.532497
        }
      ],
      "name": "custom_locations",
      "location_types": [
        "home",
        "recent"
      ]
    },
    {
      "pySocialWatcherReference": "22",
      "values": [
        {
          "latitude": 7.922621,
          "distance_unit": "kilometer",
          "radius": 1,
          "longitude": -72.494889
        }
      ],
      "name": "custom_locations",
      "location_types": [
        "home",
        "recent"
      ]
    },
    {
      "pySocialWatcherReference": "23",
      "values": [
        {
          "latitude": 7.931135,
          "distance_unit": "kilometer",
          "radius": 1,
          "longitude": -72.527622
        }
      ],
      "name": "custom_locations",
      "location_types": [
        "home",
        "recent"
      ]
    },
    {
      "pySocialWatcherReference": "24",
      "values": [
        {
          "latitude": 7.907997,
          "distance_unit": "kilometer",
          "radius": 1,
          "longitude": -72.551147
        }
      ],
      "name": "custom_locations",
      "location_types": [
        "home",
        "recent"
      ]
    },
    {
      "pySocialWatcherReference": "25",
      "values": [
        {
          "latitude": 7.862495,
          "distance_unit": "kilometer",
          "radius": 1,
          "longitude": -72.528797
        }
      ],
      "name": "custom_locations",
      "location_types": [
        "home",
        "recent"
      ]
    },
    {
      "pySocialWatcherReference": "26",
      "values": [
        {
          "latitude": 7.867379,
          "distance_unit": "kilometer",
          "radius": 1,
          "longitude": -72.510454
        }
      ],
      "name": "custom_locations",
      "location_types": [
        "home",
        "recent"
      ]
    },
    {
      "pySocialWatcherReference": "27",
      "values": [
        {
          "latitude": 7.847869,
          "distance_unit": "kilometer",
          "radius": 1,
          "longitude": -72.57521
        }
      ],
      "name": "custom_locations",
      "location_types": [
        "home",
        "recent"
      ]
    },
    {
      "pySocialWatcherReference": "28",
      "values": [
        {
          "latitude": 7.993105,
          "distance_unit": "kilometer",
          "radius": 1,
          "longitude": -72.501629
        }
      ],
      "name": "custom_locations",
      "location_types": [
        "home",
        "recent"
      ]
    },
    {
      "pySocialWatcherReference": "29",
      "values": [
        {
          "latitude": 7.941112,
          "distance_unit": "kilometer",
          "radius": 1,
          "longitude": -72.490254
        }
      ],
      "name": "custom_locations",
      "location_types": [
        "home",
        "recent"
      ]
    },
    {
      "pySocialWatcherReference": "30",
      "values": [
        {
          "latitude": 7.820132,
          "distance_unit": "kilometer",
          "radius": 1,
          "longitude": -72.51935
        }
      ],
      "name": "custom_locations",
      "location_types": [
        "home",
        "recent"
      ]
    },
    {
      "pySocialWatcherReference": "31",
      "values": [
        {
          "latitude": 7.967911,
          "distance_unit": "kilometer",
          "radius": 1,
          "longitude": -72.464413
        }
      ],
      "name": "custom_locations",
      "location_types": [
        "home",
        "recent"
      ]
    },
    {
      "pySocialWatcherReference": "32",
      "values": [
        {
          "latitude": 8.062449,
          "distance_unit": "kilometer",
          "radius": 1,
          "longitude": -72.403392
        }
      ],
      "name": "custom_locations",
      "location_types": [
        "home",
        "recent"
      ]
    },
    {
      "pySocialWatcherReference": "33",
      "values": [
        {
          "latitude": 8.234266,
          "distance_unit": "kilometer",
          "radius": 1,
          "longitude": -72.427662
        }
      ],
      "name": "custom_locations",
      "location_types": [
        "home",
        "recent"
      ]
    },
    {
      "pySocialWatcherReference": "34",
      "values": [
        {
          "latitude": 8.161456,
          "distance_unit": "kilometer",
          "radius": 1,
          "longitude": -72.46426
        }
      ],
      "name": "custom_locations",
      "location_types": [
        "home",
        "recent"
      ]
    },
    {
      "pySocialWatcherReference": "35",
      "values": [
        {
          "latitude": 8.196375,
          "distance_unit": "kilometer",
          "radius": 1,
          "longitude": -72.492808
        }
      ],
      "name": "custom_locations",
      "location_types": [
        "home",
        "recent"
      ]
    },
    {
      "pySocialWatcherReference": "36",
      "values": [
        {
          "latitude": 8.171183,
          "distance_unit": "kilometer",
          "radius": 1,
          "longitude": -72.481256
        }
      ],
      "name": "custom_locations",
      "location_types": [
        "home",
        "recent"
      ]
    },
    {
      "pySocialWatcherReference": "37",
      "values": [
        {
          "latitude": 7.848586,
          "distance_unit": "kilometer",
          "radius": 1,
          "longitude": -72.515535
        }
      ],
      "name": "custom_locations",
      "location_types": [
        "home",
        "recent"
      ]
    }
  ],
  "name": "Venezuelan Expats in Cucuta"
}